shipyard_airbyte/__init__.py
shipyard_airbyte/airbyte.py
shipyard_airbyte/cli/__init__.py
shipyard_airbyte/cli/authtest.py
shipyard_airbyte/cli/cli_determine_sync_status.py
shipyard_airbyte/cli/cli_trigger_sync.py
shipyard_airbyte-0.1.7.dist-info/METADATA
shipyard_airbyte-0.1.7.dist-info/WHEEL
shipyard_airbyte-0.1.7.dist-info/top_level.txt
shipyard_airbyte-0.1.7.dist-info/RECORD
