Metadata-Version: 2.4
Name: shipyard-airbyte
Version: 0.1.7
Summary: A local client to work with Airbyte Cloud
Requires-Python: >=3.9
Requires-Dist: requests>=2.28.0
Requires-Dist: shipyard-bp-utils>=1.0.1
Requires-Dist: shipyard-templates==0.2.0
